{
 "days": {
  "2026-07-05": {
   "total_data_jobs": 152,
   "new_today": 152,
   "failed_sources": [],
   "by_skill": {
    "SQL": 60,
    "机器学习": 60,
    "Python": 49,
    "统计学": 28,
    "Excel": 25,
    "AWS": 21,
    "A/B测试": 19,
    "Tableau": 17,
    "R": 15,
    "Power BI": 14,
    "Snowflake": 13,
    "Azure": 13,
    "dbt": 12,
    "Airflow": 10,
    "ETL": 10,
    "GCP": 8,
    "Looker": 7,
    "Spark": 7,
    "BigQuery": 5,
    "pandas": 4
   },
   "by_category": {
    "其他数据岗": 61,
    "数据分析/BI": 47,
    "数据科学/算法": 29,
    "数据开发/工程": 15
   },
   "by_region": {
    "USA": 61,
    "其他": 35,
    "欧洲": 15,
    "全球远程": 10,
    "加拿大": 9,
    "Germany": 9,
    "UK": 6,
    "拉美": 6,
    "北美": 1
   },
   "by_source": {
    "remoteok": 8,
    "remotive": 30,
    "arbeitnow": 8,
    "jobicy": 81,
    "workingnomads": 12,
    "himalayas": 12,
    "eleduck": 1
   },
   "salary_usd_year": {
    "n": 7,
    "median_min": 51900,
    "median_max": 99000
   },
   "updated_at": "2026-07-05T16:14:36+00:00"
  }
 }
}